zoo_argowf_runner/__about__.py
zoo_argowf_runner/__init__.py
zoo_argowf_runner/argo_api.py
zoo_argowf_runner/cwl2argo.py
zoo_argowf_runner/handlers.py
zoo_argowf_runner/runner.py
zoo_argowf_runner/template.py
zoo_argowf_runner/volume.py
zoo_argowf_runner/zoo_helpers.py
zoo_argowf_runner-0.1.2.dist-info/METADATA
zoo_argowf_runner-0.1.2.dist-info/WHEEL
zoo_argowf_runner-0.1.2.dist-info/RECORD
