Metadata-Version: 2.4
Name: zoo-argowf-runner
Version: 0.1.2
Summary: Zoo runner using Argo Workflows to process an Application Package encoded in CWL.
Requires-Python: >=3.8
Requires-Dist: attrs
Requires-Dist: click
Requires-Dist: cwl-utils
Requires-Dist: cwl-utils==0.14
Requires-Dist: hera
Requires-Dist: loguru
Requires-Dist: pyyaml
